datasetiq/__init__.py
datasetiq/cache.py
datasetiq/client.py
datasetiq/config.py
datasetiq/exceptions.py
datasetiq-0.1.2.dist-info/METADATA
datasetiq-0.1.2.dist-info/WHEEL
datasetiq-0.1.2.dist-info/licenses/LICENSE
datasetiq-0.1.2.dist-info/RECORD
