Metadata-Version: 2.4
Name: datasetiq
Version: 0.1.2
Summary: Official Python client for DataSetIQ — The Modern Economic Data Platform
Project-URL: Homepage, https://www.datasetiq.com
Project-URL: Documentation, https://www.datasetiq.com/docs
Project-URL: Repository, https://github.com/DataSetIQ/datasetiq-python
Project-URL: Issues, https://github.com/DataSetIQ/datasetiq-python/issues
Author-email: DataSetIQ <support@datasetiq.com>
License: MIT
License-File: LICENSE
Keywords: api,datasetiq,economic data,fred,pandas,time series
Classifier: Development Status :: 4 - Beta
Classifier: Intended Audience :: Developers
Classifier: Intended Audience :: Financial and Insurance Industry
Classifier: Intended Audience :: Science/Research
Classifier: License :: OSI Approved :: MIT License
Classifier: Programming Language :: Python :: 3
Classifier: Programming Language :: Python :: 3.9
Classifier: Programming Language :: Python :: 3.10
Classifier: Programming Language :: Python :: 3.11
Classifier: Programming Language :: Python :: 3.12
Classifier: Topic :: Office/Business :: Financial
Classifier: Topic :: Scientific/Engineering
Requires-Python: >=3.9
Requires-Dist: appdirs>=1.4.4
Requires-Dist: pandas>=1.5.0
Requires-Dist: requests>=2.31.0
Provides-Extra: dev
Requires-Dist: black>=23.7.0; extra == 'dev'
Requires-Dist: pytest-cov>=4.1.0; extra == 'dev'
Requires-Dist: pytest>=7.4.0; extra == 'dev'
Requires-Dist: responses>=0.23.0; extra == 'dev'
Requires-Dist: ruff>=0.0.285; extra == 'dev'
